
{"order":100,"items":[{"name":"Overview","href":"index.html","topicHref":"index.html"},{"name":"Accounting","href":"accounting.html","topicHref":"accounting.html"},{"name":"Cash flows","href":"cash-flows.html","topicHref":"cash-flows.html"},{"name":"Costs","href":"costs.html","topicHref":"costs.html"},{"name":"Financial analysis","href":"financial-analysis.html","topicHref":"financial-analysis.html"},{"name":"Fixed Assets","href":"fixed-assets.html","topicHref":"fixed-assets.html"},{"name":"Intrastat reporting","href":"intrastat-reporting.html","topicHref":"intrastat-reporting.html"},{"name":"Payments","href":"payments.html","topicHref":"payments.html"},{"name":"VAT reporting","href":"vat-reporting.html","topicHref":"vat-reporting.html"},{"name":"Excise Management","href":"excise.html","topicHref":"excise.html"}]}
